environexus-1.2.2.dist-info/METADATA
environexus-1.2.2.dist-info/RECORD
environexus-1.2.2.dist-info/WHEEL
environexus-1.2.2.dist-info/top_level.txt
nexus/__init__.py
