Metadata-Version: 2.1
Name: environexus
Version: 1.2.2
Summary: A library for Home Assistant to manage Zwave devices on the Environexus controller
Home-page: https://github.com/tombasche/environexus
Author: Thomas Basche
Author-email: tcbasche@gmail.com
License: UNKNOWN
Platform: UNKNOWN
Classifier: Programming Language :: Python :: 3
Classifier: License :: OSI Approved :: MIT License
Classifier: Operating System :: OS Independent
